.installed.cfg
README.txt
bootstrap.py
buildout.cfg
setup.py
src/z3c/__init__.py
src/z3c.layout.egg-info/PKG-INFO
src/z3c.layout.egg-info/SOURCES.txt
src/z3c.layout.egg-info/dependency_links.txt
src/z3c.layout.egg-info/namespace_packages.txt
src/z3c.layout.egg-info/not-zip-safe
src/z3c.layout.egg-info/requires.txt
src/z3c.layout.egg-info/top_level.txt
src/z3c/layout/README.txt
src/z3c/layout/__init__.py
src/z3c/layout/interfaces.py
src/z3c/layout/meta.zcml
src/z3c/layout/model.py
src/z3c/layout/utils.py
src/z3c/layout/zcml.py
src/z3c/layout/zcml.txt
src/z3c/layout/browser/__init__.py
src/z3c/layout/browser/insertion.py
src/z3c/layout/browser/layout.py
src/z3c/layout/tests/__init__.py
src/z3c/layout/tests/test_doctests.py
src/z3c/layout/tests/templates/default/index.html
src/z3c/layout/tests/templates/default/index.jpg
src/z3c/layout/tests/templates/default/main.css