Metadata-Version: 1.0
Name: z3c.layout
Version: 0.2
Summary: HTML layout engine
Home-page: UNKNOWN
Author: Malthe Borch, Stefan Eletzhofer and the Zope Community
Author-email: zope-dev@zope.org
License: ZPL 2.1
Keywords: zope3 layout HTML
Platform: UNKNOWN
Classifier: Development Status :: 4 - Beta
Classifier: Environment :: Web Environment
Classifier: Intended Audience :: Developers
Classifier: License :: OSI Approved :: Zope Public License
Classifier: Programming Language :: Python
Classifier: Natural Language :: English
Classifier: Operating System :: OS Independent
Classifier: Topic :: Internet :: WWW/HTTP
Classifier: Framework :: Zope3
